pooled_pika.py
pooled_pika-0.3.0.dist-info/LICENSE
pooled_pika-0.3.0.dist-info/METADATA
pooled_pika-0.3.0.dist-info/WHEEL
pooled_pika-0.3.0.dist-info/top_level.txt
pooled_pika-0.3.0.dist-info/RECORD
