Metadata-Version: 2.1
Name: pooled-pika
Version: 0.3.0
Summary: a connection pool wrapper about async pika
Home-page: https://github.com/Zephor5/pooled-pika
Author: Zephor
Author-email: zephor@qq.com
License: BSD 3-clause
Requires-Python: >=3.7,<3.10
License-File: LICENSE
Requires-Dist: twisted (~=22.10.0)
Requires-Dist: pika (~=1.3.0)
